turta_relayhat2/Turta_Relay.py
turta_relayhat2/__init__.py
turta_relayhat2-1.0.2.dist-info/LICENCE
turta_relayhat2-1.0.2.dist-info/METADATA
turta_relayhat2-1.0.2.dist-info/WHEEL
turta_relayhat2-1.0.2.dist-info/top_level.txt
turta_relayhat2-1.0.2.dist-info/RECORD
