Metadata-Version: 2.1
Name: turta-relayhat2
Version: 1.0.2
Summary: Python Libraries for Turta Relay HAT 2
Home-page: https://www.turta.io/relayhat
Author: Turta LLC
Author-email: hello@turta.io
License: UNKNOWN
Project-URL: Documentation, https://docs.turta.io/raspberry-pi-hats/relay-hat-2
Project-URL: Community, https://community.turta.io
Project-URL: GitHub Repository, https://github.com/Turta-io/RelayHAT2
Platform: UNKNOWN
Classifier: Development Status :: 5 - Production/Stable
Classifier: Intended Audience :: Developers
Classifier: Programming Language :: Python
Classifier: License :: OSI Approved :: MIT License
Classifier: Operating System :: Unix
Classifier: Topic :: System :: Hardware
Requires-Dist: smbus
